holm-0.8.1.dist-info/METADATA
holm-0.8.1.dist-info/WHEEL
holm-0.8.1.dist-info/entry_points.txt
holm-0.8.1.dist-info/licenses/LICENSE
holm/__init__.py
holm/_model.py
holm/app.py
holm/fastapi.py
holm/logging.py
holm/module_options/__init__.py
holm/module_options/_actions.py
holm/module_options/_metadata.py
holm/module_options/_submit_handler.py
holm/modules/__init__.py
holm/modules/_api.py
holm/modules/_error.py
holm/modules/_layout.py
holm/modules/_page.py
holm/py.typed
holm/typing.py
holm-0.8.1.dist-info/RECORD
