Metadata-Version: 2.1
Name: holm
Version: 0.8.1
Summary: Web development framework that brings the Next.js developer experience to Python, built on FastAPI, htmy, and FastHX.
Requires-Python: >=3.10
Requires-Dist: fastapi>=0.115.12
Requires-Dist: fasthx>=3.0.1
Requires-Dist: htmy[lxml]>=0.8.2
Requires-Dist: python-multipart>=0.0.20
